pyiron_contrib/__init__.py
pyiron_contrib/_version.py
pyiron_contrib/RDM/__init__.py
pyiron_contrib/RDM/storagejob.py
pyiron_contrib/atomistics/__init__.py
pyiron_contrib/atomistics/atomistics/__init__.py
pyiron_contrib/atomistics/atomistics/job/__init__.py
pyiron_contrib/atomistics/atomistics/job/structurelistmasterinteractive.py
pyiron_contrib/atomistics/atomistics/master/__init__.py
pyiron_contrib/atomistics/atomistics/master/qha.py
pyiron_contrib/atomistics/cp2k/__init__.py
pyiron_contrib/atomistics/cp2k/job.py
pyiron_contrib/atomistics/dft/__init__.py
pyiron_contrib/atomistics/dft/parametermaster.py
pyiron_contrib/atomistics/elastic/__init__.py
pyiron_contrib/atomistics/elastic/elastic.py
pyiron_contrib/atomistics/interactive/__init__.py
pyiron_contrib/atomistics/interactive/intermixer.py
pyiron_contrib/atomistics/interactive/langevin.py
pyiron_contrib/atomistics/interactive/mixer.py
pyiron_contrib/atomistics/interactive/montecarlo.py
pyiron_contrib/atomistics/lammps/__init__.py
pyiron_contrib/atomistics/lammps/drag.py
pyiron_contrib/atomistics/lammps/potentials.py
pyiron_contrib/atomistics/randspg/__init__.py
pyiron_contrib/atomistics/randspg/randspg.py
pyiron_contrib/generic/__init__.py
pyiron_contrib/generic/coscineIo.py
pyiron_contrib/generic/filedata.py
pyiron_contrib/generic/s3io.py
pyiron_contrib/generic/storage_interface_toolkit.py
pyiron_contrib/image/__init__.py
pyiron_contrib/image/custom_filters.py
pyiron_contrib/image/image.py
pyiron_contrib/image/job.py
pyiron_contrib/image/utils.py
pyiron_contrib/jobfactories/__init__.py
pyiron_contrib/protocol/__init__.py
pyiron_contrib/protocol/generic.py
pyiron_contrib/protocol/list.py
pyiron_contrib/protocol/math.py
pyiron_contrib/protocol/compound/__init__.py
pyiron_contrib/protocol/compound/finite_temperature_string.py
pyiron_contrib/protocol/compound/minimize.py
pyiron_contrib/protocol/compound/molecular_dynamics.py
pyiron_contrib/protocol/compound/nudged_elastic_band.py
pyiron_contrib-0.1.19.dist-info/licenses/LICENSE
pyiron_contrib-0.1.19.dist-info/METADATA
pyiron_contrib-0.1.19.dist-info/WHEEL
pyiron_contrib-0.1.19.dist-info/top_level.txt
pyiron_contrib-0.1.19.dist-info/RECORD
